keywords_en/__init__.py
keywords_en/cli.py
keywords_en/keywords_en.py
keywords_en/utils/__init__.py
keywords_en/utils/key_bert_kw.py
keywords_en/utils/stop_keywords.py
keywords_en/utils/text_rank_kw.py
keywords_en/utils/tf_idf_kw.py
keywords_en/utils/topic_rank_kw.py
keywords_en/utils/yake_kw.py
keywords_en-0.3.0.dist-info/AUTHORS.rst
keywords_en-0.3.0.dist-info/LICENSE
keywords_en-0.3.0.dist-info/METADATA
keywords_en-0.3.0.dist-info/WHEEL
keywords_en-0.3.0.dist-info/entry_points.txt
keywords_en-0.3.0.dist-info/top_level.txt
keywords_en-0.3.0.dist-info/RECORD
