Metadata-Version: 2.1
Name: keywords-en
Version: 0.3.0
Summary: keywords extract
Home-page: https://github.com/nilecui/keywords_en
Author: nilecui
Author-email: nilecui@gmail.com
License: GNU General Public License v3
Keywords: keywords_en
Platform: UNKNOWN
Classifier: Development Status :: 2 - Pre-Alpha
Classifier: Intended Audience :: Developers
Classifier: License :: OSI Approved :: GNU General Public License v3 (GPLv3)
Classifier: Natural Language :: English
Classifier: Programming Language :: Python :: 3
Classifier: Programming Language :: Python :: 3.6
Classifier: Programming Language :: Python :: 3.7
Classifier: Programming Language :: Python :: 3.8
Requires-Python: >=3.6
License-File: LICENSE
License-File: AUTHORS.rst
Requires-Dist: anyio (==3.6.1)
Requires-Dist: argon2-cffi (==21.3.0)
Requires-Dist: argon2-cffi-bindings (==21.2.0)
Requires-Dist: asgiref (==3.4.1)
Requires-Dist: async-generator (==1.10)
Requires-Dist: attrs (==22.1.0)
Requires-Dist: backcall (==0.2.0)
Requires-Dist: backports-datetime-fromisoformat (==1.0.0)
Requires-Dist: backports.zoneinfo (==0.2.1)
Requires-Dist: bleach (==4.1.0)
Requires-Dist: certifi (==2022.6.15)
Requires-Dist: cffi (==1.15.1)
Requires-Dist: charset-normalizer (==2.0.12)
Requires-Dist: click (==8.0.4)
Requires-Dist: commonmark (==0.9.1)
Requires-Dist: contextlib2 (==21.6.0)
Requires-Dist: contextvars (==2.4)
Requires-Dist: courlan (==0.8.3)
Requires-Dist: dataclasses (==0.8)
Requires-Dist: dateparser (==1.1.1)
Requires-Dist: decorator (==4.2.1)
Requires-Dist: defusedxml (==0.7.1)
Requires-Dist: entrypoints (==0.4)
Requires-Dist: fastapi (==0.79.0)
Requires-Dist: filelock (==3.4.1)
Requires-Dist: h11 (==0.13.0)
Requires-Dist: htmldate (==1.3.0)
Requires-Dist: huggingface-hub (==0.4.0)
Requires-Dist: idna (==3.3)
Requires-Dist: immutables (==0.18)
Requires-Dist: importlib-metadata (==4.8.3)
Requires-Dist: importlib-resources (==5.4.0)
Requires-Dist: ipykernel (==5.5.6)
Requires-Dist: ipython (==7.16.3)
Requires-Dist: ipython-genutils (==0.2.0)
Requires-Dist: ipywidgets (==7.7.1)
Requires-Dist: jedi (==0.17.2)
Requires-Dist: jellyfish (==0.9.0)
Requires-Dist: Jinja2 (==3.0.3)
Requires-Dist: joblib (==1.1.0)
Requires-Dist: jsonschema (==3.2.0)
Requires-Dist: jupyter-client (==7.1.2)
Requires-Dist: jupyter-core (==4.9.2)
Requires-Dist: jupyterlab-pygments (==0.1.2)
Requires-Dist: jupyterlab-widgets (==1.1.1)
Requires-Dist: jusText (==3.0.0)
Requires-Dist: keybert (==0.6.0)
Requires-Dist: keywords-en (==0.1.0)
Requires-Dist: langcodes (==3.3.0)
Requires-Dist: langdetect (==1.0.7)
Requires-Dist: lxml (==4.9.1)
Requires-Dist: MarkupSafe (==2.0.1)
Requires-Dist: mistune (==0.8.4)
Requires-Dist: nbclient (==0.5.9)
Requires-Dist: nbconvert (==6.0.7)
Requires-Dist: nbformat (==5.1.3)
Requires-Dist: nest-asyncio (==1.5.5)
Requires-Dist: networkx (==2.1)
Requires-Dist: nltk (==3.6.6)
Requires-Dist: notebook (==6.4.10)
Requires-Dist: numpy (==1.17.0)
Requires-Dist: packaging (==21.3)
Requires-Dist: pandocfilters (==1.5.0)
Requires-Dist: parso (==0.7.1)
Requires-Dist: pexpect (==4.8.0)
Requires-Dist: pickleshare (==0.7.5)
Requires-Dist: Pillow (==8.4.0)
Requires-Dist: prometheus-client (==0.14.1)
Requires-Dist: prompt-toolkit (==3.0.30)
Requires-Dist: ptyprocess (==0.7.0)
Requires-Dist: pycparser (==2.21)
Requires-Dist: pydantic (==1.9.2)
Requires-Dist: Pygments (==2.12.0)
Requires-Dist: pyparsing (==3.0.9)
Requires-Dist: pyrsistent (==0.18.0)
Requires-Dist: python-dateutil (==2.8.2)
Requires-Dist: pytz (==2022.2)
Requires-Dist: pytz-deprecation-shim (==0.1.0.post0)
Requires-Dist: PyYAML (==6.0)
Requires-Dist: pyzmq (==23.2.1)
Requires-Dist: regex (==2022.3.2)
Requires-Dist: requests (==2.27.1)
Requires-Dist: rich (==12.5.1)
Requires-Dist: sacremoses (==0.0.53)
Requires-Dist: scikit-learn (==0.19.1)
Requires-Dist: scipy (==1.0.0)
Requires-Dist: segtok (==1.5.11)
Requires-Dist: Send2Trash (==1.8.0)
Requires-Dist: sentence-transformers (==2.2.2)
Requires-Dist: sentencepiece (==0.1.97)
Requires-Dist: six (==1.11.0)
Requires-Dist: sniffio (==1.2.0)
Requires-Dist: starlette (==0.19.1)
Requires-Dist: summa (==1.2.0)
Requires-Dist: tabulate (==0.8.10)
Requires-Dist: terminado (==0.12.1)
Requires-Dist: testpath (==0.6.0)
Requires-Dist: threadpoolctl (==3.1.0)
Requires-Dist: tld (==0.12.6)
Requires-Dist: tokenizers (==0.12.1)
Requires-Dist: torch (==1.10.1)
Requires-Dist: torchvision (==0.11.2)
Requires-Dist: tornado (==6.1)
Requires-Dist: tqdm (==4.64.0)
Requires-Dist: trafilatura (==1.3.0)
Requires-Dist: traitlets (==4.3.3)
Requires-Dist: transformers (==4.18.0)
Requires-Dist: typing-extensions (==4.1.1)
Requires-Dist: tzdata (==2022.1)
Requires-Dist: tzlocal (==4.2)
Requires-Dist: urllib3 (==1.26.11)
Requires-Dist: uvicorn (==0.16.0)
Requires-Dist: wcwidth (==0.2.5)
Requires-Dist: webencodings (==0.5.1)
Requires-Dist: widgetsnbextension (==3.6.1)
Requires-Dist: zipp (==3.6.0)
